TurboTalk/__init__.py
TurboTalk/main.py
TurboTalk-0.1.6.dist-info/METADATA
TurboTalk-0.1.6.dist-info/WHEEL
TurboTalk-0.1.6.dist-info/top_level.txt
TurboTalk-0.1.6.dist-info/RECORD
